{
  "backgroundTexture": "Fondos/FondoJuego.png",
  "dialogueFile": "Dialogos/Dialogos_personajes.json",
  "groundTexture": "Environment/FloorWhite320.png",
  "levelWidth": 2800,
  "playerStartX": 32,
  "playerStartY": 32,
  "nextLevel": "Levels/Level 1.json",
  "solidObjectsData": [

    { "type":"Chain_White_Type1", "x": 150, "y": 96, "walkable": false },
    { "type":"Chain_White_Type2", "x": 238, "y": 96, "walkable": false },
    { "type":"Chain_White_Type3", "x": 326, "y": 96, "walkable": false },
    { "type":"Chain_White_Type4", "x": 414, "y": 96, "walkable": false },

    { "type": "Platform_White_Small", "x": 150, "y": 80 },
    { "type": "Platform_White_Small", "x": 238, "y": 144 },
    { "type": "Platform_White_Small", "x": 326, "y": 208 },
    { "type": "Platform_White_Small", "x": 326, "y": 80 },



    { "type":"Chain_White_Type2", "x": 722, "y": 96, "walkable": false },
    { "type":"Chain_White_Type2", "x": 938, "y": 96, "walkable": false },

    { "type": "Platform_White_Large", "x": 722, "y": 80 },
    { "type": "Platform_White_Large", "x": 722, "y": 144 },


    
    { "type":"Chain_White_Type3", "x": 1246, "y": 96, "walkable": false },
    { "type":"Chain_White_Type3", "x": 1398, "y": 96, "walkable": false },
    { "type":"Chain_White_Type3", "x": 1456, "y": 96, "walkable": false },
    { "type":"Chain_White_Type3", "x": 1544, "y": 96, "walkable": false },

    { "type": "Platform_White_Medium", "x": 1246, "y": 80 },
    { "type": "Platform_White_Medium", "x": 1246, "y": 144 },
    { "type": "Platform_White_Medium", "x": 1246, "y": 208 },
    { "type": "Platform_White_Small", "x": 1456, "y": 80 },
    { "type": "Platform_White_Small", "x": 1456, "y": 144 },
    { "type": "Platform_White_Small", "x": 1456, "y": 208 },



    { "type":"Chain_White_Type1", "x": 1852, "y": 96, "walkable": false },
    { "type":"Chain_White_Type1", "x": 1908, "y": 96, "walkable": false },
    { "type":"Chain_White_Type1", "x": 1966, "y": 96, "walkable": false },
    { "type":"Chain_White_Type1", "x": 2022, "y": 96, "walkable": false },
    { "type":"Chain_White_Type1", "x": 2080, "y": 96, "walkable": false },
    { "type":"Chain_White_Type1", "x": 2136, "y": 96, "walkable": false },

    { "type": "Platform_White_Tiny", "x": 1852, "y": 80 },
    { "type": "Platform_White_Tiny", "x": 1966, "y": 80 },
    { "type": "Platform_White_Tiny", "x": 2080, "y": 80 },



    { "type":"Chain_White_Type1", "x": 2444, "y": 96, "walkable": false },
    { "type":"Chain_White_Type1", "x": 2724, "y": 96, "walkable": false },

    { "type": "Platform_White_Huge", "x": 2444, "y": 80 }
  ],
  "enemies": [
    
    { "type": "PATROLLER", "x": 772, "y": 144, "patrolPoints": [{"x": 906, "y": 144, "action": "Fall"}, {"x": 772, "y": 96, "action": "Jump"}]},
    { "type": "PATROLLER", "x": 906, "y": 96, "patrolPoints": [{"x": 772, "y": 96, "action": "Jump"}, {"x": 906, "y": 144, "action": "Fall"}]},

    { "type": "FLYING", "x": 1411, "y": 96, "patrolPoints": [{"x": 1411, "y": 224}, {"x": 1411, "y": 96}]},
    { "type": "FLYING", "x": 1557, "y": 224, "patrolPoints": [{"x": 1557, "y": 96}, {"x": 1557, "y": 224}]},
    
    { "type": "SHOOTER", "x": 2092, "y": 96},

    { "type": "PATROLLER", "x": 2492, "y": 96 },
    { "type": "PATROLLER", "x": 2532, "y": 96 },
    { "type": "PATROLLER", "x": 2572, "y": 96 },
    { "type": "PATROLLER", "x": 2612, "y": 96 },
    { "type": "PATROLLER", "x": 2652, "y": 96 },
    { "type": "PATROLLER", "x": 2692, "y": 96 }
  ],
  "npcs": [
    
    { "idleFrames": "NPC/Info-Bot/Info-BotIdle", "x": 110, "y": 72, "dialogues": ["TUTORIAL_1"] },

    { "idleFrames": "NPC/Info-Bot/Info-BotIdle", "x": 682, "y": 72, "dialogues": ["TUTORIAL_2"] },

    { "idleFrames": "NPC/Info-Bot/Info-BotIdle", "x": 1206, "y": 72, "dialogues": ["TUTORIAL_3"] },

    { "idleFrames": "NPC/Info-Bot/Info-BotIdle", "x": 1812, "y": 72, "dialogues": ["TUTORIAL_4"] },

    { "idleFrames": "NPC/Info-Bot/Info-BotIdle", "x": 2404, "y": 72, "dialogues": ["TUTORIAL_5"] }
  ]
}